[
  {
    "recurso": "reccurso",
    "funciona": "funciona.",
    "simples": "cimples"
  },
  {
    "arquitetura": "arquitertura",
    "sistema": "cistema",
    "tecnologia": "tecnolgia"
  },
  {
    "desenvolvimento": "desenvolvmento",
    "arquitetura": "arquiteturra",
    "melhor": "melhorr"
  },
  {
    "arquitetura": "arquitretura",
    "tecnologia": "tecnnologia"
  },
  {
    "controle": "contrle",
    "sistema": "sistma"
  },
  {
    "automatizado": "automatizdo.",
    "necessidade": "nescessidade",
    "arquitetura": "arquitretura"
  },
  {
    "exemplo": "exemplo.",
    "desenvolvimento": "desenvolmento",
    "sistema": "cistema"
  },
  {
    "processo": "processso",
    "controle": "controlle"
  },
  {
    "monitoramento": "monitramento",
    "prioridade": "prioriade."
  },
  {
    "propriedade": "propriedade.",
    "estrutura": "estrututra",
    "desafio": "desafiu"
  },
  {
    "resultado": "resultao",
    "suporte": "suportte",
    "melhor": "melhorr"
  },
  {
    "abordagem": "abordajem",
    "arquitetura": "arquiteturra",
    "desenvolvimento": "desenvolmento"
  },
  {
    "geralmente": "geralmemte",
    "funcionalidade": "funcionaliadde",
    "tecnologia": "tecnnologia"
  },
  {
    "tecnologia": "tecnolgia",
    "sistema": "sistma"
  },
  {
    "processo": "proceso",
    "desenvolvimento": "desenvolvimente",
    "tecnologia": "tecnoligia"
  },
  {
    "armazenamento": "armazanamento",
    "abordagem": "abordajem",
    "arquitetura": "arquitertura"
  },
  {
    "gerenciamento": "gerenciamente",
    "processo": "processso"
  },
  {
    "arquitetura": "arquiteturra",
    "tecnologia": "tecnolgia",
    "desenvolvimento": "desenvolvmento"
  },
  {
    "constante": "constante.",
    "tecnologia": "tecnoligia",
    "abordagem": "abordajem"
  },
  {
    "tecnologia": "tecnolgia",
    "simples": "simplis"
  }
]