[
  {
    "monitoramento": "monitoramento.",
    "abordagem": "abordagem."
  },
  {
    "sistema": "cistema",
    "necessidade": "necessidade.",
    "muito": "muto"
  },
  {
    "processo": "processso",
    "recurso": "reccurso",
    "necessidade": "nescessidade"
  },
  {
    "arquitetura": "arquitertura",
    "desenvolvimento": "desenvolvimente",
    "controle": "controle."
  },
  {
    "armazenamento": "armazanamento",
    "exemplo": "exemplo,"
  },
  {
    "sistema": "sistéma",
    "desafio": "desafío"
  },
  {
    "simples": "simplis",
    "processo": "proceso"
  },
  {
    "acesso": "aceso",
    "muito": "muto",
    "melhor": "melhorr"
  },
  {
    "rotina": "rotína",
    "internet": "internert",
    "dispositivo": "disposotivo"
  },
  {
    "constante": "constante.",
    "simples": "simlpes",
    "exemplo": "exemplo,"
  },
  {
    "virtual": "virtual.",
    "muito": "muiito"
  },
  {
    "prioridade": "prioriade.",
    "desenvolvimento": "desenvolvimente"
  },
  {
    "estrutura": "estrura",
    "consistente": "consiteente",
    "tecnologia": "tecnoligia"
  },
  {
    "problema": "probrema",
    "arquitetura": "arquitertura",
    "sistema": "sistéma"
  },
  {
    "arquitetura": "arquitretura",
    "constante": "constanate"
  },
  {
    "abordagem": "abordajem",
    "necessidade": "nescessidade",
    "acesso": "acesso."
  },
  {
    "funciona": "funciona.",
    "controle": "controlle"
  },
  {
    "arquitetura": "arquitertura",
    "desenvolvimento": "desenvolvmento",
    "funciona": "funsiona"
  },
  {
    "funcionalidade": "funcionalidade.",
    "utilizado": "utilizdo",
    "muito": "muiito"
  },
  {
    "paralelo": "paralélo",
    "componente": "componete",
    "processo": "processso"
  }
]