[
  {
    "exemplo": "exenplo",
    "sistema": "sistma",
    "monitoramento": "monitoramento."
  },
  {
    "melhor": "melhorr",
    "controle": "controle."
  },
  {
    "operacional": "operaciona",
    "armazenamento": "armasenamento"
  },
  {
    "necessidade": "necessidade.",
    "sistema": "sistéma",
    "monitoramento": "monitoramento."
  },
  {
    "abordagem": "abordajem",
    "melhor": "melhorr",
    "resultado": "resutlado"
  },
  {
    "computador": "computador.",
    "melhor": "melor",
    "muito": "muto"
  },
  {
    "tecnologia": "tecnoligia",
    "desenvolvimento": "desenvolmento",
    "arquitetura": "arquitretura"
  },
  {
    "sistema": "sistéma",
    "gerenciamento": "gerenciamente",
    "monitoramento": "monitoramento."
  },
  {
    "muito": "muinto",
    "tecnologia": "tecnnologia"
  },
  {
    "arquitetura": "arquiteturra",
    "tecnologia": "tecnolgia",
    "monitoramento": "monitoramento."
  },
  {
    "prioridade": "prioriade.",
    "sistema": "sistéma",
    "desenvolvimento": "desenvolvimente"
  },
  {
    "constante": "constate",
    "desenvolvimento": "desenvolvmento"
  },
  {
    "desafio": "desaío",
    "problema": "probrema",
    "dispositivo": "disposotivo"
  },
  {
    "funcionalidade": "funcionalidade."
  },
  {
    "necessidade": "necessidade.",
    "operacional": "operacional.",
    "sistema": "sistma"
  },
  {
    "constante": "constante.",
    "necessidade": "nescessidade",
    "tecnologia": "tecnnologia"
  },
  {
    "desafio": "desafío",
    "arquitetura": "arquiteturra"
  },
  {
    "componente": "componete",
    "processo": "processso",
    "desenvolvimento": "desenvolmento"
  },
  {
    "virtual": "virtual.",
    "funciona": "funciona."
  },
  {
    "estrutura": "estrura",
    "desafio": "desaío",
    "tecnologia": "tecnnologia"
  }
]