[
  {
    "problema": "problema.",
    "exemplo": "exenplo",
    "desafio": "desaío"
  },
  {
    "abordagem": "abordagem.",
    "arquitetura": "arquitretura"
  },
  {
    "constante": "constante.",
    "complexidade": "complexsidade",
    "exemplo": "exemplo."
  },
  {
    "tecnologia": "tecnolgia",
    "funciona": "funciona."
  },
  {
    "suporte": "suprte",
    "controle": "controle."
  },
  {
    "abordagem": "abordajem",
    "arquitetura": "arquitretura"
  },
  {
    "muito": "muinto",
    "prioridade": "prioridade."
  },
  {
    "resultado": "resutlado",
    "arquitetura": "arquitertura",
    "funcionalidade": "funcionaliade"
  },
  {
    "simples": "simlpes",
    "dispositivo": "disposotivo",
    "muito": "muiito"
  },
  {
    "necessidade": "nescessidade",
    "geralmente": "geralmete"
  },
  {
    "armazenamento": "armazenamentto",
    "arquitetura": "arquitretura",
    "sistema": "sistéma"
  },
  {
    "internet": "internete",
    "tecnologia": "tecnoligia",
    "exemplo": "exenplo"
  },
  {
    "sistema": "sistma",
    "arquitetura": "arquitertura",
    "funciona": "funsiona"
  },
  {
    "melhor": "melhorr",
    "dispositivo": "disposotivo"
  },
  {
    "recurso": "reccurso",
    "gerenciamento": "gerenciamneto",
    "exemplo": "exenplo"
  },
  {
    "carregamento": "carregamento.",
    "tecnologia": "tecnolgia",
    "necessidade": "nescessidade"
  },
  {
    "sistema": "sistéma",
    "exemplo": "exemplo.",
    "complexidade": "complexidade."
  },
  {
    "processo": "proceso",
    "simples": "simlpes",
    "controle": "controle."
  },
  {
    "desenvolvimento": "desenvolmento",
    "exemplo": "exenplo"
  },
  {
    "rotina": "rotna",
    "monitoramento": "monitorameto",
    "dispositivo": "disposotivo"
  }
]