[
  {
    "desafio": "desafiu",
    "necessidade": "necessidade."
  },
  {
    "recurso": "recusso",
    "problema": "probrema"
  },
  {
    "resultado": "resultao",
    "tecnologia": "tecnoligia"
  },
  {
    "acesso": "aceso",
    "simples": "cimples"
  },
  {
    "gerenciamento": "gerenciamneto",
    "complexidade": "complexidade.",
    "arquitetura": "arquiteturra"
  },
  {
    "processo": "processso",
    "desenvolvimento": "desenvolvmento",
    "tecnologia": "tecnoligia"
  },
  {
    "propriedade": "propriadade",
    "operacional": "operaciona",
    "prioridade": "prioriade."
  },
  {
    "melhor": "melhorr",
    "arquitetura": "arquiteturra"
  },
  {
    "sistema": "sistma",
    "exemplo": "exemplo."
  },
  {
    "tecnologia": "tecnoligia",
    "desafio": "desafiu",
    "funciona": "funciona."
  },
  {
    "muito": "muto",
    "geralmente": "geralmemte"
  },
  {
    "arquitetura": "arquitertura",
    "funcionalidade": "funcionaliade"
  },
  {
    "suporte": "suporte.",
    "melhor": "melhorr",
    "recurso": "reccurso"
  },
  {
    "dispositivo": "dispotivo",
    "arquitetura": "arquitretura"
  },
  {
    "monitoramento": "monitoramento.",
    "arquitetura": "arquiteturra",
    "complexidade": "complezidade"
  },
  {
    "conhecimento": "conhecimento.",
    "arquitetura": "arquitretura",
    "desenvolvimento": "desenvolvimente"
  },
  {
    "arquitetura": "arquitertura"
  },
  {
    "estrutura": "estrututra",
    "exemplo": "exemplo.",
    "funciona": "funsiona"
  },
  {
    "armazenamento": "armasenamento",
    "melhor": "melor"
  },
  {
    "abordagem": "abordage",
    "operacional": "operacional.",
    "conhecimento": "conhecimeto"
  }
]