[
  {
    "complexidade": "complezidade",
    "necessidade": "necissidade",
    "arquitetura": "arquitretura"
  },
  {
    "conectado": "conetado",
    "sistema": "sistma"
  },
  {
    "suporte": "suprte",
    "abordagem": "abordagem.",
    "arquitetura": "arquitertura"
  },
  {
    "arquitetura": "arquiteturra",
    "desafio": "desafiu",
    "funcionalidade": "funcionaliadde"
  },
  {
    "constante": "constate",
    "arquitetura": "arquitertura",
    "controle": "contrle"
  },
  {
    "melhor": "melor",
    "internet": "internete",
    "exemplo": "exemplo,"
  },
  {
    "arquitetura": "arquiteturra",
    "tecnologia": "tecnoligia",
    "funciona": "funciona."
  },
  {
    "tecnologia": "tecnnologia",
    "funciona": "funsiona"
  },
  {
    "exemplo": "exemplo,",
    "melhor": "melhorr",
    "tecnologia": "tecnolgia"
  },
  {
    "virtual": "virtuaal",
    "internet": "internert",
    "problema": "poblema"
  },
  {
    "arquitetura": "arquitertura",
    "abordagem": "abordajem"
  },
  {
    "propriedade": "propriadade",
    "conhecimento": "conhescimento"
  },
  {
    "abordagem": "abordajem",
    "desenvolvimento": "desenvolvmento",
    "arquitetura": "arquiteturra"
  },
  {
    "componente": "componente.",
    "armazenamento": "armazanamento",
    "monitoramento": "monitorameto"
  },
  {
    "tecnologia": "tecnoligia",
    "acesso": "acesço",
    "melhor": "melhorr"
  },
  {
    "arquitetura": "arquitretura",
    "sistema": "sistma"
  },
  {
    "resultado": "resutlado",
    "arquitetura": "arquitertura",
    "monitoramento": "monitramento"
  },
  {
    "monitoramento": "monitoramento.",
    "arquitetura": "arquiteturra",
    "necessidade": "nescessidade"
  },
  {
    "gerenciamento": "gerenciamneto",
    "arquitetura": "arquitertura"
  },
  {
    "executado": "execudado",
    "problema": "poblema"
  }
]