[
  {
    "monitoramento": "monitorameto",
    "tecnologia": "tecnoligia",
    "constante": "constate"
  },
  {
    "estrutura": "estrututra",
    "tecnologia": "tecnnologia",
    "processo": "proceso"
  },
  {
    "gerenciamento": "gerenciamneto",
    "sistema": "sistma"
  },
  {
    "dispositivo": "disposotivo",
    "necessidade": "necessidade.",
    "abordagem": "abordajem"
  },
  {
    "parceria": "parcería",
    "exemplo": "exenplo"
  },
  {
    "controle": "controlle",
    "arquitetura": "arquitretura",
    "prioridade": "prioriade"
  },
  {
    "arquitetura": "arquitertura",
    "desenvolvimento": "desenvolvimente"
  },
  {
    "operacional": "operacional.",
    "sistema": "sistéma"
  },
  {
    "conectado": "conetado",
    "acesso": "acesso."
  },
  {
    "funcionalidade": "funcionaliadde"
  },
  {
    "muito": "muto",
    "sistema": "sistéma",
    "tecnologia": "tecnoligia"
  },
  {
    "monitoramento": "monitorameto",
    "funcionalidade": "funcionaliadde",
    "melhor": "melor"
  },
  {
    "recurso": "recusso",
    "tecnologia": "tecnnologia"
  },
  {
    "internet": "internat",
    "funciona": "funciona,"
  },
  {
    "virtual": "virtuaal",
    "utilizado": "utilizdo",
    "consistente": "consiteente"
  },
  {
    "sistema": "cistema",
    "tecnologia": "tecnolgia",
    "monitoramento": "monitorameto"
  },
  {
    "desafio": "desafío",
    "suporte": "suportte",
    "arquitetura": "arquitertura"
  },
  {
    "armazenamento": "armazenamentto",
    "internet": "internete"
  },
  {
    "arquitetura": "arquiteturra",
    "desenvolvimento": "desenvolvimente",
    "tecnologia": "tecnolgia"
  },
  {
    "desenvolvimento": "desenvolmento",
    "tecnologia": "tecnoligia",
    "parceria": "parceria."
  }
]