[
  {
    "sistema": "sistéma",
    "muito": "muiito"
  },
  {
    "funcionalidade": "funcionalidade.",
    "exemplo": "exemplo,",
    "desenvolvimento": "desenvolmento"
  },
  {
    "problema": "probrema",
    "necessidade": "nescessidade"
  },
  {
    "armazenamento": "armazanamento",
    "prioridade": "prioriade.",
    "tecnologia": "tecnolgia"
  },
  {
    "constante": "constanate",
    "sistema": "sistéma",
    "exemplo": "exenplo"
  },
  {
    "estrutura": "estrututra",
    "sistema": "sistma",
    "funciona": "funciona,"
  },
  {
    "simples": "simplis",
    "prioridade": "prioriade.",
    "monitoramento": "monitorameto"
  },
  {
    "arquitetura": "arquitertura",
    "prioridade": "prioriade",
    "necessidade": "nescessidade"
  },
  {
    "conhecimento": "conhescimento",
    "tecnologia": "tecnoligia"
  },
  {
    "tecnologia": "tecnolgia",
    "monitoramento": "monitorameto",
    "necessidade": "necessidade."
  },
  {
    "dispositivo": "dispositivo.",
    "internet": "internat"
  },
  {
    "sistema": "sistéma",
    "simples": "simplis",
    "muito": "muinto"
  },
  {
    "exemplo": "exemplo.",
    "muito": "muiito",
    "melhor": "melor"
  },
  {
    "funcionalidade": "funcionalidade.",
    "controle": "controle.",
    "dispositivo": "disposotivo"
  },
  {
    "simples": "simplis",
    "exemplo": "exemplo.",
    "desenvolvimento": "desenvolvimente"
  },
  {
    "abordagem": "abordage",
    "resultado": "resultadoo"
  },
  {
    "conhecimento": "conhecimento.",
    "desenvolvimento": "desenvolvimente",
    "muito": "muto"
  },
  {
    "recurso": "recusso",
    "suporte": "suportte",
    "processo": "proceso"
  },
  {
    "exemplo": "exenplo",
    "desenvolvimento": "desenvolvmento",
    "conhecimento": "conhecimento."
  },
  {
    "monitoramento": "monitorameto",
    "abordagem": "abordajem",
    "problema": "poblema"
  }
]