[
  {
    "exemplo": "exemplo,",
    "acesso": "acesço"
  },
  {
    "carregamento": "carregamento.",
    "internet": "internete",
    "utilizado": "utilizdo"
  },
  {
    "controle": "controlle",
    "desenvolvimento": "desenvolvmento",
    "resultado": "resultadoo"
  },
  {
    "armazenamento": "armazanamento"
  },
  {
    "sistema": "sistéma",
    "simples": "simlpes"
  },
  {
    "muito": "muto",
    "acesso": "aceso",
    "tecnologia": "tecnnologia"
  },
  {
    "recurso": "recuro",
    "complexidade": "complexidade."
  },
  {
    "sistema": "sistéma",
    "arquitetura": "arquitretura",
    "desenvolvimento": "desenvolmento"
  },
  {
    "funcionalidade": "funcionaliade",
    "suporte": "suportte",
    "exemplo": "exenplo"
  },
  {
    "simples": "cimples",
    "melhor": "melhorr",
    "sistema": "sistéma"
  },
  {
    "arquitetura": "arquitertura",
    "desenvolvimento": "desenvolmento",
    "melhor": "melor"
  },
  {
    "funciona": "funciona.",
    "prioridade": "prioriade.",
    "sistema": "sistma"
  },
  {
    "automatizado": "automatizdo.",
    "rotina": "rotína",
    "tecnologia": "tecnolgia"
  },
  {
    "geralmente": "geralmemte",
    "controle": "controlle",
    "tecnologia": "tecnnologia"
  },
  {
    "virtual": "virtuaal",
    "utilizado": "utilizdo"
  },
  {
    "exemplo": "exemplo,",
    "melhor": "melhorr",
    "funciona": "funsiona"
  },
  {
    "monitoramento": "monitramento",
    "arquitetura": "arquitertura"
  },
  {
    "abordagem": "abordagem.",
    "tecnologia": "tecnoligia"
  },
  {
    "arquitetura": "arquitertura",
    "funcionalidade": "funcionaliadde"
  },
  {
    "simples": "simplis",
    "tecnologia": "tecnnologia",
    "arquitetura": "arquiteturra"
  }
]