[
  {
    "melhor": "melhorr",
    "processo": "processso",
    "necessidade": "necessidade."
  },
  {
    "consistente": "consistente.",
    "monitoramento": "monitramento"
  },
  {
    "conhecimento": "conhescimento",
    "melhor": "melhorr"
  },
  {
    "executado": "executado.",
    "armazenamento": "armazanamento",
    "operacional": "operacionl"
  },
  {
    "complexidade": "complezidade",
    "componente": "componete",
    "necessidade": "necessidade."
  },
  {
    "exemplo": "exenplo",
    "arquitetura": "arquiteturra",
    "constante": "constante."
  },
  {
    "estrutura": "estrura",
    "tecnologia": "tecnoligia",
    "arquitetura": "arquitretura"
  },
  {
    "resultado": "resutlado",
    "simples": "simplis"
  },
  {
    "desenvolvimento": "desenvolvimente",
    "controle": "controlle"
  },
  {
    "gerenciamento": "gerenciamneto",
    "funciona": "funciona,",
    "correto": "corretoo"
  },
  {
    "virtual": "virtual.",
    "dispositivo": "disposotivo",
    "tecnologia": "tecnoligia"
  },
  {
    "suporte": "suportte",
    "funcionalidade": "funcionaliadde",
    "tecnologia": "tecnnologia"
  },
  {
    "funcionalidade": "funcionaliade",
    "desenvolvimento": "desenvolvimente",
    "suporte": "suporte."
  },
  {
    "problema": "poblema",
    "carregamento": "carregameno",
    "internet": "internert"
  },
  {
    "dispositivo": "dispotivo",
    "sistema": "sistma",
    "melhor": "melhorr"
  },
  {
    "muito": "muto",
    "sistema": "cistema"
  },
  {
    "tecnologia": "tecnnologia",
    "funcionalidade": "funcionaliadde"
  },
  {
    "suporte": "suportte"
  },
  {
    "acesso": "acesço",
    "tecnologia": "tecnolgia",
    "controle": "controlle"
  },
  {
    "parceria": "parcería",
    "desafio": "desaío",
    "complexidade": "complexsidade"
  }
]