[
  {
    "dispositivo": "dispositivo.",
    "gerenciamento": "gerenciamneto",
    "desenvolvimento": "desenvolvmento"
  },
  {
    "dispositivo": "disposotivo",
    "gerenciamento": "gerenciamnto"
  },
  {
    "arquitetura": "arquitertura",
    "suporte": "suporte."
  },
  {
    "funciona": "funsiona",
    "funcionalidade": "funcionaliadde"
  },
  {
    "acesso": "aceso",
    "conhecimento": "conhecimento.",
    "tecnologia": "tecnoligia"
  },
  {
    "abordagem": "abordage",
    "controle": "contrle",
    "acesso": "acesso."
  },
  {
    "funciona": "funciona.",
    "tecnologia": "tecnnologia",
    "recurso": "recuro"
  },
  {
    "constante": "constate",
    "funciona": "funciona,",
    "melhor": "melhorr"
  },
  {
    "propriedade": "proprieade",
    "funciona": "funciona.",
    "simples": "cimples"
  },
  {
    "monitoramento": "monitorameto",
    "simples": "simlpes"
  },
  {
    "arquitetura": "arquiteturra",
    "tecnologia": "tecnolgia",
    "muito": "muinto"
  },
  {
    "processo": "processso",
    "abordagem": "abordage",
    "arquitetura": "arquitertura"
  },
  {
    "desenvolvimento": "desenvolvmento",
    "sistema": "cistema",
    "abordagem": "abordagem."
  },
  {
    "resultado": "resutlado",
    "melhor": "melor",
    "processo": "prosseso"
  },
  {
    "melhor": "melhorr",
    "tecnologia": "tecnoligia",
    "exemplo": "exemplo,"
  },
  {
    "armazenamento": "armazenamentto",
    "dispositivo": "dispositivo.",
    "gerenciamento": "gerenciamneto"
  },
  {
    "desenvolvimento": "desenvolvimente",
    "sistema": "sistéma",
    "exemplo": "exenplo"
  },
  {
    "executado": "excutado",
    "simples": "simlpes",
    "arquitetura": "arquitretura"
  },
  {
    "abordagem": "abordagem.",
    "gerenciamento": "gerenciamente",
    "desenvolvimento": "desenvolvimente"
  },
  {
    "problema": "problema.",
    "arquitetura": "arquitretura",
    "monitoramento": "monitoramento."
  }
]